erppeek.py
ERPpeek-1.7.1.dist-info/LICENSE
ERPpeek-1.7.1.dist-info/METADATA
ERPpeek-1.7.1.dist-info/WHEEL
ERPpeek-1.7.1.dist-info/entry_points.txt
ERPpeek-1.7.1.dist-info/top_level.txt
ERPpeek-1.7.1.dist-info/RECORD
