Metadata-Version: 1.1
Name: ERPpeek
Version: 1.7.1
Summary: Versatile tool for browsing Odoo / OpenERP data
Home-page: http://erppeek.readthedocs.org/
Author: Florent Xicluna
Author-email: florent.xicluna@gmail.com
License: BSD
Keywords: odoo openerp xml-rpc xmlrpc
Platform: any
Classifier: Development Status :: 5 - Production/Stable
Classifier: Environment :: Console
Classifier: Intended Audience :: Developers
Classifier: License :: OSI Approved :: BSD License
Classifier: Operating System :: OS Independent
Classifier: Programming Language :: Python
Classifier: Programming Language :: Python :: 2
Classifier: Programming Language :: Python :: 3
Classifier: Topic :: Software Development :: Libraries :: Python Modules
